{"host":"mail.webappsactualized.com","fromEmail":"billing@webappsactualized.com","fromName":"Greg Goad","to":"info@zehlm.com","subject":"1 Receipt","body":"<h2>1 Receipt<\/h2><br\/><br\/>\n\t\n\tHello Zehlm Web Development, LLC, <br\/><br\/>\n\t<h4>Special Note<\/h4><br\/>I'll be moving to the next thing ASAP.<br\/><br\/>\n\t<b>Thank you for your business<\/b>. Attached to this email should be 1 Receipt for a total of: <b>$110.00<\/b>.<br\/><br\/>\n\t\n\t<h3>Details<\/h3><br\/>Payment ID: 2 for $110.00 on October 22, 2022 for the job Dryvco<br\/><br\/><br\/><br\/>As of the time of this mailing, your current outstanding balance is: <b>$0.00<\/b><br\/><br\/><br\/><br\/><i>Thank You<\/i>, <br\/>\n\t   Web Apps Actualized<br\/><br\/>\n\t   <h3>Do not reply to this email. <\/h3>Replies to this email are not checked.\n\t   <br\/><br\/>\n\t   <h4>Contact Information<\/h4>\n\t   Phone: 336-406-1319","attachments":["\/home\/webapp19\/public_html\/..\/waaBillingSecure\/mailings\/3\/2.pdf"],"CCs":["ggoadmusic+waaBilling@gmail.com"],"errorMessage":""}